[
  {
    "type": "event",
    "anonymous": false,
    "name": "BridgeStarted",
    "inputs": [
      {
        "type": "bytes",
        "name": "transactionId",
        "indexed": true
      },
      {
        "type": "address",
        "name": "user",
        "indexed": true
      },
      {
        "type": "bytes",
        "name": "receiver",
        "indexed": false
      },
      {
        "type": "string",
        "name": "bridge",
        "indexed": false
      },
      {
        "type": "address",
        "name": "bridgeAddress",
        "indexed": false
      },
      {
        "type": "address",
        "name": "from",
        "indexed": false
      },
      {
        "type": "bytes",
        "name": "to",
        "indexed": false
      },
      {
        "type": "uint256",
        "name": "amount",
        "indexed": false
      },
      {
        "type": "uint256",
        "name": "destinationChainId",
        "indexed": false
      },
      {
        "type": "bool",
        "name": "hasDestinationCall",
        "indexed": false
      }
    ]
  },
  {
    "type": "event",
    "anonymous": false,
    "name": "DZapBatchTokenSwapped",
    "inputs": [
      {
        "type": "bytes",
        "name": "transactionId",
        "indexed": true
      },
      {
        "type": "address",
        "name": "sender",
        "indexed": true
      },
      {
        "type": "tuple[]",
        "name": "swapInfo",
        "components": [
          {
            "type": "string",
            "name": "dex"
          },
          {
            "type": "address",
            "name": "callTo"
          },
          {
            "type": "address",
            "name": "recipient"
          },
          {
            "type": "address",
            "name": "fromToken"
          },
          {
            "type": "address",
            "name": "toToken"
          },
          {
            "type": "uint256",
            "name": "fromAmount"
          },
          {
            "type": "uint256",
            "name": "returnToAmount"
          }
        ]
      }
    ]
  },
  {
    "type": "event",
    "anonymous": false,
    "name": "DZapBridgeStarted",
    "inputs": [
      {
        "type": "bytes",
        "name": "transactionId",
        "indexed": true
      },
      {
        "type": "address",
        "name": "user",
        "indexed": true
      },
      {
        "type": "address",
        "name": "integrator",
        "indexed": true
      }
    ]
  },
  {
    "type": "event",
    "anonymous": false,
    "name": "DZapTokenSwapped",
    "inputs": [
      {
        "type": "bytes",
        "name": "transactionId",
        "indexed": true
      },
      {
        "type": "address",
        "name": "sender",
        "indexed": true
      },
      {
        "type": "tuple",
        "name": "swapInfo",
        "indexed": false,
        "components": [
          {
            "type": "string",
            "name": "dex"
          },
          {
            "type": "address",
            "name": "callTo"
          },
          {
            "type": "address",
            "name": "recipient"
          },
          {
            "type": "address",
            "name": "fromToken"
          },
          {
            "type": "address",
            "name": "toToken"
          },
          {
            "type": "uint256",
            "name": "fromAmount"
          },
          {
            "type": "uint256",
            "name": "returnToAmount"
          }
        ]
      }
    ]
  },
  {
    "type": "event",
    "anonymous": false,
    "name": "DZapGasLessStarted",
    "inputs": [
      {
        "type": "bytes",
        "name": "_transactionId",
        "indexed": true
      },
      {
        "type": "address",
        "name": "executor",
        "indexed": true
      },
      {
        "type": "address",
        "name": "_user",
        "indexed": true
      }
    ]
  },
  {
    "type": "event",
    "anonymous": false,
    "name": "RelayBridgeTransferStarted",
    "inputs": [
      {
        "type": "bytes",
        "name": "transactionId",
        "indexed": true
      },
      {
        "type": "address",
        "name": "user",
        "indexed": true
      },
      {
        "type": "bytes",
        "name": "reciever",
        "indexed": false
      },
      {
        "type": "address",
        "name": "from",
        "indexed": false
      },
      {
        "type": "bytes",
        "name": "to",
        "indexed": false
      },
      {
        "type": "tuple",
        "name": "relayData",
        "indexed": false,
        "components": [
          {
            "type": "uint256",
            "name": "amountIn"
          },
          {
            "type": "bytes32",
            "name": "requestId"
          }
        ]
      },
      {
        "type": "uint256",
        "name": "destinationChainId",
        "indexed": false
      },
      {
        "type": "bool",
        "name": "hasDestinationCall",
        "indexed": false
      }
    ]
  },
  {
    "type": "event",
    "anonymous": false,
    "name": "GasZipBridgeTransferStarted",
    "inputs": [
      {
        "type": "bytes",
        "name": "transactionId",
        "indexed": true
      },
      {
        "type": "address",
        "name": "user",
        "indexed": true
      },
      {
        "type": "tuple",
        "name": "gasZipData",
        "indexed": false,
        "components": [
          {
            "type": "bytes32",
            "name": "recipient"
          },
          {
            "type": "uint256",
            "name": "destChains"
          },
          {
            "type": "uint256",
            "name": "depositAmount"
          }
        ]
      },
      {
        "type": "bool",
        "name": "hasDestinationCall",
        "indexed": false
      }
    ]
  }
]